{"stats":{"minecraft:crafted":{"minecraft:gold_ingot":54,"minecraft:air":0},"minecraft:dropped":{"minecraft:diamond_axe":1,"minecraft:glass_bottle":2,"cobblemon:oran_berry":2},"minecraft:used":{"minecraft:torch":1,"minecraft:nether_bricks":1,"minecraft:wither_rose":1,"minecraft:air":18},"minecraft:custom":{"minecraft:open_chest":1,"minecraft:time_since_rest":52925,"minecraft:crouch_one_cm":4744,"minecraft:interact_with_furnace":11,"minecraft:play_time":52925,"minecraft:sprint_one_cm":68477,"minecraft:damage_taken":140,"minecraft:walk_one_cm":54712,"minecraft:sneak_time":686,"cobblemon:dex_entries":6,"minecraft:walk_under_water_one_cm":175,"minecraft:pot_flower":1,"cobblemon:level_up":34,"minecraft:drop":5,"minecraft:jump":365,"minecraft:interact_with_brewingstand":1,"cobblemon:times_ridden":5,"minecraft:walk_on_water_one_cm":4399,"minecraft:leave_game":2,"minecraft:time_since_death":52925,"minecraft:climb_one_cm":473,"minecraft:total_world_time":52925,"cobblemon:battles_total":9,"minecraft:swim_one_cm":9236,"minecraft:fall_one_cm":5695,"minecraft:fly_one_cm":35142},"minecraft:picked_up":{"cobblemon:yellow_apricorn":7,"tmcraft:tm_poisonfang":1,"cobblemon:guard_spec":2,"minecraft:diamond_axe":1,"cobbleversebadges:kanto_soul_badge":1,"cobblemon:oran_berry":2,"minecraft:glass_bottle":2},"minecraft:mined":{"minecraft:birch_leaves":18}},"DataVersion":3955}